sphinx_pyviz_theme/__init__.py
sphinx_pyviz_theme/_version.py
sphinx_pyviz_theme/layout.html
sphinx_pyviz_theme/search.html
sphinx_pyviz_theme/theme.conf
sphinx_pyviz_theme/includes/ga.html
sphinx_pyviz_theme/includes/searchbox.html
sphinx_pyviz_theme/static/css/main.css_t
sphinx_pyviz_theme/static/images/favicon.ico
sphinx_pyviz_theme/static/images/logo.png
sphinx_pyviz_theme/static/js/main.js
sphinx_pyviz_theme-0.0.5.dist-info/LICENSE.txt
sphinx_pyviz_theme-0.0.5.dist-info/METADATA
sphinx_pyviz_theme-0.0.5.dist-info/WHEEL
sphinx_pyviz_theme-0.0.5.dist-info/entry_points.txt
sphinx_pyviz_theme-0.0.5.dist-info/top_level.txt
sphinx_pyviz_theme-0.0.5.dist-info/RECORD
