Metadata-Version: 2.1
Name: sphinx-pyviz-theme
Version: 0.0.5
Summary: Theme for building pyviz sites; best when used with nbsite.
Home-page: https://github.com/pyviz-dev/sphinx_pyviz_theme
License: BSD-3
Platform: UNKNOWN
Requires-Python: >=2.7
Requires-Dist: sphinx
